{
    "whyMeData": [
        {
            "title": "Fast",
            "content": "I am fast in completing work according to a predetermined schedule.",
            "color": "danger"
        },
        {
            "title": "Guarantee",
            "content": "I guarantee that every job I do will be optimal and satisfying. If you are not satisfied? I am ready to discuss with you to improve it until you are completely satisfied.",
            "color": "warning"
        },
        {
            "title": "Favourite",
            "content": "During my time as a Freelancer, my clients are very happy with the work I do.",
            "color": "info"
        }
    ]
}